max_chatbot_python/__init__.py
max_chatbot_python/bot.py
max_chatbot_python/filters.py
max_chatbot_python/manager/__init__.py
max_chatbot_python/manager/handler.py
max_chatbot_python/manager/observer.py
max_chatbot_python/manager/router.py
max_chatbot_python/manager/state.py
max_chatbot_python-1.0.0.dist-info/LICENSE
max_chatbot_python-1.0.0.dist-info/METADATA
max_chatbot_python-1.0.0.dist-info/WHEEL
max_chatbot_python-1.0.0.dist-info/top_level.txt
max_chatbot_python-1.0.0.dist-info/RECORD
